{
    "shi": 2.13766,
    "health_percent": 72.15,
    "location": "NEW YORK, USA",
    "collapse_type": "SUPPLY CHAIN BREAK",
    "collapse_timer": "48:21:02",
    "bottlenecks": [
        {
            "loc": "Beijing, China",
            "deviation": "Trade barriers"
        },
        {
            "loc": "Riyadh, Saudi Arabia",
            "deviation": "Energy chokepoints"
        },
        {
            "loc": "London, UK",
            "deviation": "High debt"
        }
    ],
    "high_shi": [
        {
            "loc": "Singapore, Singapore",
            "protocol": "Policy reforms"
        },
        {
            "loc": "Stockholm, Sweden",
            "protocol": "Anti-corruption"
        },
        {
            "loc": "San Francisco, USA",
            "protocol": "Innovation"
        }
    ],
    "scroller_feed": "CRITICAL: NEW YORK, USA TARGETED FOR SUPPLY CHAIN BREAK | ECONOMIC INDICATORS SHOW SIGNS OF INSTABILITY, TRADE NEGOTIATIONS UNDERWAY, AND A NEW TECH HUB UNVEILED IN THE CITY.",
    "last_updated": "2026-03-14 10:49:24",
    "formula_metrics": {
        "N": 1.44,
        "P": 0.82,
        "F": 0.91,
        "T": 0.75,
        "B": 0.65,
        "C": 0.58
    }
}