{
    "shi": 2.71111,
    "health_percent": 74.21,
    "location": "NEW YORK, USA",
    "collapse_type": "SUPPLY CHAIN BREAK",
    "collapse_timer": "48:21:12",
    "bottlenecks": [
        {
            "loc": "Beijing, China",
            "deviation": "High debt and energy dependence"
        },
        {
            "loc": "Tokyo, Japan",
            "deviation": "Trade barriers and aging population"
        },
        {
            "loc": "Moscow, Russia",
            "deviation": "Inefficient governance and high corruption"
        }
    ],
    "high_shi": [
        {
            "loc": "Singapore",
            "protocol": "Robust policy reforms"
        },
        {
            "loc": "San Francisco, USA",
            "protocol": "Strong innovation culture"
        },
        {
            "loc": "Zurich, Switzerland",
            "protocol": "Effective anti-corruption measures"
        }
    ],
    "scroller_feed": "CRITICAL: NEW YORK, USA TARGETED FOR SUPPLY CHAIN BREAK | GLOBAL MARKETS EXPERIENCING HIGH VOLATILITY, TRADE TENSIONS RISING BETWEEN MAJOR ECONOMIES, AND ENERGY PRICES FLUCTUATING WILDLY",
    "last_updated": "2026-03-18 21:03:00",
    "formula_metrics": {
        "N": 1.44,
        "P": 0.85,
        "F": 1.23,
        "T": 1.11,
        "B": 0.67,
        "C": 0.92
    }
}