{
    "shi": 0.78209,
    "health_percent": 72.19,
    "location": "NEW YORK, USA",
    "collapse_type": "SUPPLY CHAIN BREAK",
    "collapse_timer": "47:12:01",
    "bottlenecks": [
        {
            "loc": "Beijing, China",
            "deviation": "High debt"
        },
        {
            "loc": "Istanbul, Turkey",
            "deviation": "Energy chokepoints"
        },
        {
            "loc": "London, UK",
            "deviation": "Trade barriers"
        }
    ],
    "high_shi": [
        {
            "loc": "Singapore",
            "protocol": "Innovation hub"
        },
        {
            "loc": "Zurich, Switzerland",
            "protocol": "Policy reforms"
        },
        {
            "loc": "Vancouver, Canada",
            "protocol": "Anti-corruption"
        }
    ],
    "scroller_feed": "CRITICAL: NEW YORK, USA TARGETED FOR SUPPLY CHAIN BREAK | GLOBAL MARKETS EXPERIENCING HIGH VOLATILITY, TRADE TENSIONS ON THE RISE",
    "last_updated": "2026-03-16 23:51:36",
    "formula_metrics": {
        "N": 1.44,
        "P": 0.87,
        "F": 0.92,
        "T": 0.78,
        "B": 1.21,
        "C": 0.95
    }
}