{
    "shi": 1.20507,
    "health_percent": 74.21,
    "location": "NEW YORK, USA",
    "collapse_type": "SUPPLY CHAIN BREAK",
    "collapse_timer": "43:21:02",
    "bottlenecks": [
        {
            "loc": "Shanghai, China",
            "deviation": "Over-reliance on imports"
        },
        {
            "loc": "Rotterdam, Netherlands",
            "deviation": "Energy shortages"
        },
        {
            "loc": "Tokyo, Japan",
            "deviation": "High public debt"
        }
    ],
    "high_shi": [
        {
            "loc": "Singapore",
            "protocol": "Innovation hub"
        },
        {
            "loc": "Zurich, Switzerland",
            "protocol": "Strong financial regulations"
        },
        {
            "loc": "Copenhagen, Denmark",
            "protocol": "Sustainable energy practices"
        }
    ],
    "scroller_feed": "CRITICAL: NEW YORK, USA TARGETED FOR SUPPLY CHAIN BREAK | BREAKING NEWS: GLOBAL MARKETS EXPERIENCE SLIGHT DOWNTURN DUE TO TRADE TENSIONS; EXPERTS PREDICT POTENTIAL SUPPLY CHAIN DISRUPTIONS.",
    "last_updated": "2026-03-21 23:01:09",
    "formula_metrics": {
        "N": 1.44,
        "P": 0.85,
        "F": 0.92,
        "T": 1.01,
        "B": 1.21,
        "C": 0.78
    }
}