{
    "shi": 2.28502,
    "health_percent": 73.21,
    "location": "NEW YORK, USA",
    "collapse_type": "SUPPLY CHAIN BREAK",
    "collapse_timer": "48:22:13",
    "bottlenecks": [
        {
            "loc": "Beijing, China",
            "deviation": "High energy demand"
        },
        {
            "loc": "Suez, Egypt",
            "deviation": "Trade barrier"
        },
        {
            "loc": "Dubai, UAE",
            "deviation": "Debt servicing issues"
        }
    ],
    "high_shi": [
        {
            "loc": "Singapore",
            "protocol": "Innovation hubs"
        },
        {
            "loc": "Zurich, Switzerland",
            "protocol": "Anti-corruption policies"
        },
        {
            "loc": "Copenhagen, Denmark",
            "protocol": "Sustainable energy initiatives"
        }
    ],
    "scroller_feed": "CRITICAL: NEW YORK, USA TARGETED FOR SUPPLY CHAIN BREAK | GLOBAL MARKETS EXPERIENCING HIGH VOLATILITY, OIL PRICES SURGE DUE TO MIDDLE EAST TENSIONS.",
    "last_updated": "2026-03-21 20:15:22",
    "formula_metrics": {
        "N": 1.44,
        "P": 0.85,
        "F": 1.21,
        "T": 0.92,
        "B": 0.67,
        "C": 0.89
    }
}