{
    "shi": 0.99274,
    "health_percent": 73.42,
    "location": "NEW YORK, USA",
    "collapse_type": "SUPPLY CHAIN BREAK",
    "collapse_timer": "48:02:15",
    "bottlenecks": [
        {
            "loc": "Beijing, China",
            "deviation": "High Debt"
        },
        {
            "loc": "Dubai, UAE",
            "deviation": "Energy Chokepoints"
        },
        {
            "loc": "Tokyo, Japan",
            "deviation": "Trade Barriers"
        }
    ],
    "high_shi": [
        {
            "loc": "Singapore, Singapore",
            "protocol": "Innovation"
        },
        {
            "loc": "Zurich, Switzerland",
            "protocol": "Policy Reforms"
        },
        {
            "loc": "Copenhagen, Denmark",
            "protocol": "Anti-Corruption"
        }
    ],
    "scroller_feed": "CRITICAL: NEW YORK, USA TARGETED FOR SUPPLY CHAIN BREAK | GLOBAL ECONOMIC INSTABILITY ON THE RISE, TRADE TENSIONS ESCALATING BETWEEN MAJOR NATIONS.",
    "last_updated": "2026-03-26 20:53:38",
    "formula_metrics": {
        "N": 1.44,
        "P": 0.75,
        "F": 0.92,
        "T": 0.81,
        "B": 1.21,
        "C": 0.67
    }
}