{
    "shi": 1.59299,
    "health_percent": 68.25,
    "location": "NEW YORK, USA",
    "collapse_type": "SUPPLY CHAIN BREAK",
    "collapse_timer": "48:21:09",
    "bottlenecks": [
        {
            "loc": "Beijing, China",
            "deviation": "Trade barriers"
        },
        {
            "loc": "Moscow, Russia",
            "deviation": "High debt"
        },
        {
            "loc": "Tehran, Iran",
            "deviation": "Energy chokepoints"
        }
    ],
    "high_shi": [
        {
            "loc": "Singapore",
            "protocol": "Anti-corruption reforms"
        },
        {
            "loc": "Stockholm, Sweden",
            "protocol": "Innovation clusters"
        },
        {
            "loc": "Zurich, Switzerland",
            "protocol": "Policy reforms"
        }
    ],
    "scroller_feed": "CRITICAL: NEW YORK, USA TARGETED FOR SUPPLY CHAIN BREAK | GLOBAL TRADE VOLUME DECREASED BY 5% DUE TO ONGOING LOGISTICS DISRUPTIONS; ECONOMIC STIMULUS PACKAGES PROPOSED IN MULTIPLE COUNTRIES TO MITIGATE IMPACT OF TRADE BARRIERS.",
    "last_updated": "2026-04-25 15:54:05",
    "formula_metrics": {
        "N": 1.44,
        "P": 0.87,
        "F": 0.92,
        "T": 0.85,
        "B": 0.75,
        "C": 0.82
    }
}