{
    "shi": 1.56123,
    "health_percent": 73.21,
    "location": "NEW YORK, USA",
    "collapse_type": "SUPPLY CHAIN BREAK",
    "collapse_timer": "48:21:01",
    "bottlenecks": [
        {
            "loc": "Beijing, China",
            "deviation": "High debt levels and trade barriers"
        },
        {
            "loc": "Moscow, Russia",
            "deviation": "Energy chokepoints and geopolitical tensions"
        },
        {
            "loc": "Caracas, Venezuela",
            "deviation": "Hyper-inflation and economic instability"
        }
    ],
    "high_shi": [
        {
            "loc": "Singapore",
            "protocol": "Innovative trade policies and anti-corruption reforms"
        },
        {
            "loc": "Zurich, Switzerland",
            "protocol": "Strong financial regulations and stable economic growth"
        },
        {
            "loc": "Copenhagen, Denmark",
            "protocol": "Sustainable energy solutions and social welfare policies"
        }
    ],
    "scroller_feed": "CRITICAL: NEW YORK, USA TARGETED FOR SUPPLY CHAIN BREAK | GLOBAL ECONOMIC UNCERTAINTY ON THE RISE, TRADE TENSIONS BETWEEN MAJOR ECONOMIES ESCALATING, AND CONCERNS OVER SUPPLY CHAIN DISRUPTIONS GROWING.",
    "last_updated": "2026-03-29 17:31:31",
    "formula_metrics": {
        "N": 1.44,
        "P": 0.83,
        "F": 1.21,
        "T": 0.95,
        "B": 1.1,
        "C": 0.8
    }
}