{
    "shi": 1.08344,
    "health_percent": 72.15,
    "location": "NEW YORK, USA",
    "collapse_type": "HYPER-INFLATION",
    "collapse_timer": "48:21:42",
    "bottlenecks": [
        {
            "loc": "Beijing, China",
            "deviation": "Trade barriers"
        },
        {
            "loc": "Dubai, UAE",
            "deviation": "Energy chokepoints"
        },
        {
            "loc": "Tokyo, Japan",
            "deviation": "High debt"
        }
    ],
    "high_shi": [
        {
            "loc": "Singapore",
            "protocol": "Policy reforms"
        },
        {
            "loc": "Zurich, Switzerland",
            "protocol": "Innovation"
        },
        {
            "loc": "Copenhagen, Denmark",
            "protocol": "Anti-corruption"
        }
    ],
    "scroller_feed": "CRITICAL: NEW YORK, USA TARGETED FOR HYPER-INFLATION | GLOBAL MARKETS FLUCTUATING WILDLY, INVESTORS SEEK SAFE HAVENS.",
    "last_updated": "2026-04-17 21:54:26",
    "formula_metrics": {
        "N": 1.44,
        "P": 0.85,
        "F": 0.92,
        "T": 0.78,
        "B": 1.21,
        "C": 0.67
    }
}