{
    "shi": 2.52,
    "scroller_feed": "\ud83d\udd34 BOTTLENECKS: Global supply chains face unprecedented disruptions due to rising tensions and logistical failures. Economic instability and environmental degradation pose significant threats to international trade and development. \ud83d\udfe2 PROTOCOLS: GHI introduces the 'Green Solutions' framework, comprising three core protocols: (1) 'Smart Logistics' to optimize supply chain efficiency, (2) 'Eco-Friendly Infrastructure' to reduce environmental impact, and (3) 'Digital Diplomacy' to facilitate international cooperation and conflict resolution.",
    "status": "MEGA_CIRCUIT_ACTIVE",
    "last_updated": "2026-03-13 13:04:36",
    "formula_metrics": {
        "N": 0.8,
        "P": 0.7,
        "F": 0.9,
        "T": 0.6,
        "B": 0.4,
        "C": 0.3
    }
}