{
    "shi": 1.79002,
    "health_percent": 67.32,
    "location": "NEW YORK, USA",
    "collapse_type": "HYPER-INFLATION",
    "collapse_timer": "48:21:42",
    "bottlenecks": [
        {
            "loc": "Beijing, China",
            "deviation": "energy chokepoint"
        },
        {
            "loc": "London, UK",
            "deviation": "high debt"
        },
        {
            "loc": "Mumbai, India",
            "deviation": "trade barriers"
        }
    ],
    "high_shi": [
        {
            "loc": "Singapore, Singapore",
            "protocol": "policy reforms"
        },
        {
            "loc": "Zurich, Switzerland",
            "protocol": "anti-corruption"
        },
        {
            "loc": "San Francisco, USA",
            "protocol": "innovation"
        }
    ],
    "scroller_feed": "CRITICAL: NEW YORK, USA TARGETED FOR HYPER-INFLATION | GLOBAL ECONOMIC INDICATORS EXPERIENCING SIGNIFICANT FLUCTUATIONS, MULTIPLE TRADE AGREEMENTS UNDER REVIEW",
    "last_updated": "2026-05-21 08:18:50",
    "formula_metrics": {
        "N": 1.44,
        "P": 0.83,
        "F": 0.92,
        "T": 1.05,
        "B": 0.75,
        "C": 0.86
    }
}