{
    "shi": 0.77048,
    "health_percent": 67.32,
    "location": "TOKYO, JAPAN",
    "collapse_type": "SUPPLY CHAIN BREAK",
    "collapse_timer": "48:21:10",
    "bottlenecks": [
        {
            "loc": "Beijing, China",
            "deviation": "High debt and trade barriers"
        },
        {
            "loc": "New York, USA",
            "deviation": "Energy chokepoints and corruption"
        },
        {
            "loc": "London, UK",
            "deviation": "High inflation and economic instability"
        }
    ],
    "high_shi": [
        {
            "loc": "Singapore",
            "protocol": "Robust policy reforms and innovation"
        },
        {
            "loc": "Zurich, Switzerland",
            "protocol": "Strong anti-corruption and economic stability"
        },
        {
            "loc": "Vancouver, Canada",
            "protocol": "Diversified economy and sustainable growth"
        }
    ],
    "scroller_feed": "CRITICAL: TOKYO, JAPAN TARGETED FOR SUPPLY CHAIN BREAK | ECONOMIC INSTABILITY IN EUROPE, TRADE TENSIONS BETWEEN US AND CHINA, AND RISING DEBT IN EMERGING MARKETS",
    "last_updated": "2026-04-16 08:56:25",
    "formula_metrics": {
        "N": 1.44,
        "P": 0.85,
        "F": 0.92,
        "T": 0.78,
        "B": 1.2,
        "C": 0.95
    }
}