{
    "shi": 3.21737,
    "health_percent": 73.21,
    "location": "NEW YORK, USA",
    "collapse_type": "SUPPLY CHAIN BREAK",
    "collapse_timer": "48:21:02",
    "bottlenecks": [
        {
            "loc": "Beijing, China",
            "deviation": "High Debt"
        },
        {
            "loc": "Moscow, Russia",
            "deviation": "Energy Chokepoint"
        },
        {
            "loc": "Lagos, Nigeria",
            "deviation": "Trade Barriers"
        }
    ],
    "high_shi": [
        {
            "loc": "Singapore",
            "protocol": "Innovation Hub"
        },
        {
            "loc": "Copenhagen, Denmark",
            "protocol": "Policy Reforms"
        },
        {
            "loc": "Vancouver, Canada",
            "protocol": "Anti-Corruption Measures"
        }
    ],
    "scroller_feed": "CRITICAL: NEW YORK, USA TARGETED FOR SUPPLY CHAIN BREAK | GLOBAL MARKETS EXPERIENCING FLUCTUATIONS, ECONOMISTS WARNING OF POTENTIAL DOWNTURN. ONGOING TRADE NEGOTIATIONS BETWEEN MAJOR NATIONS. INNOVATION IN RENEWABLE ENERGY ON THE RISE.",
    "last_updated": "2026-06-10 11:57:14",
    "formula_metrics": {
        "N": 1.44,
        "P": 0.85,
        "F": 0.92,
        "T": 0.78,
        "B": 0.65,
        "C": 0.42
    }
}